pysvdrp/__init__.py
pysvdrp/channels.py
pysvdrp/epg.py
pysvdrp/exceptions.py
pysvdrp/plugins.py
pysvdrp/tools.py
pysvdrp-0.0.1.dist-info/LICENSE
pysvdrp-0.0.1.dist-info/METADATA
pysvdrp-0.0.1.dist-info/WHEEL
pysvdrp-0.0.1.dist-info/top_level.txt
pysvdrp-0.0.1.dist-info/RECORD
