Metadata-Version: 2.1
Name: pysvdrp
Version: 0.0.1
Summary: Python library to control VDR via the SVDRP protocol
Home-page: https://github.com/M-Reimer/pysvdrp
Author: Manuel Reimer
Author-email: manuel.reimer@gmx.de
License: UNKNOWN
Platform: UNKNOWN
Classifier: Programming Language :: Python :: 3
Classifier: License :: OSI Approved :: GNU Lesser General Public License v3 or later (LGPLv3+)
Classifier: Operating System :: OS Independent
Requires-Python: >=3.6
Requires-Dist: cchardet
